bunsetsu/__init__.py
bunsetsu/chunker.py
bunsetsu/integrations.py
bunsetsu/tokenizer.py
bunsetsu-0.1.0.dist-info/METADATA
bunsetsu-0.1.0.dist-info/WHEEL
bunsetsu-0.1.0.dist-info/licenses/LICENSE
bunsetsu-0.1.0.dist-info/RECORD
