Metadata-Version: 2.4
Name: bunsetsu
Version: 0.1.0
Summary: Japanese-optimized semantic text chunking for RAG applications
Project-URL: Homepage, https://github.com/YUALAB/bunsetsu
Project-URL: Documentation, https://github.com/YUALAB/bunsetsu#readme
Project-URL: Repository, https://github.com/YUALAB/bunsetsu
Project-URL: Issues, https://github.com/YUALAB/bunsetsu/issues
Author-email: YUA LAB <desk@aquallc.jp>
License-Expression: MIT
License-File: LICENSE
Keywords: japanese,langchain,llamaindex,llm,nlp,rag,semantic-chunking,text-chunking
Classifier: Development Status :: 4 - Beta
Classifier: Intended Audience :: Developers
Classifier: License :: OSI Approved :: MIT License
Classifier: Natural Language :: Japanese
Classifier: Programming Language :: Python :: 3
Classifier: Programming Language :: Python :: 3.9
Classifier: Programming Language :: Python :: 3.10
Classifier: Programming Language :: Python :: 3.11
Classifier: Programming Language :: Python :: 3.12
Classifier: Topic :: Scientific/Engineering :: Artificial Intelligence
Classifier: Topic :: Text Processing :: Linguistic
Requires-Python: >=3.9
Provides-Extra: all
Requires-Dist: fugashi>=1.3.0; extra == 'all'
Requires-Dist: sudachidict-core>=20240109; extra == 'all'
Requires-Dist: sudachipy>=0.6.8; extra == 'all'
Requires-Dist: unidic-lite>=1.0.8; extra == 'all'
Provides-Extra: dev
Requires-Dist: pytest-cov>=4.0; extra == 'dev'
Requires-Dist: pytest>=7.0; extra == 'dev'
Requires-Dist: ruff>=0.1.0; extra == 'dev'
Provides-Extra: mecab
Requires-Dist: fugashi>=1.3.0; extra == 'mecab'
Requires-Dist: unidic-lite>=1.0.8; extra == 'mecab'
Provides-Extra: sudachi
Requires-Dist: sudachidict-core>=20240109; extra == 'sudachi'
Requires-Dist: sudachipy>=0.6.8; extra == 'sudachi'
